{
    "transactions": [
      {
        "id": 1,
        "type": "income",
        "description": "Freelance Payment",
        "amount": 5000.00
      },
      {
        "id": 2,
        "type": "income",
        "description": "Rent Payment",
        "amount": 1200.00
      },
      {
        "id": 3,
        "type": "expense",
        "description": "Groceries",
        "amount": 200.00
      },
      {
        "id": 4,
        "type": "expense",
        "description": "Gas",
        "amount": 50.00
      },
      {
        "id": 5,
        "type": "expense",
        "description": "Internet Bill",
        "amount": 75.00
      }
    ]
  }